{"size_train": 127775, "size_test": 65915, "number_classes_train_noun": 4470, "number_classes_train_verb": 114, "number_classes_test_noun": 3520, "number_classes_test_verb": 116, "list_classes_train_noun": ["throw", "aspirin", "vinayaga", "doorway", "beer", "awesimbook", "sweat", "fax", "spatula", "chocolates", "wrench", "brownie", "badge", "nintendo", "tooth-paste", "astray", "balm", "trapper", "street", "cotton", "miller", "spiral", "single", "horse", "doyle", "puff", "sub", "marigold", "talkto", "microcontroller", "castle", "monster", "upper", "oilcan", "leaf", "sheath", "inch", "feed", "dam", "dangle", "window", "burrito", "sweatshirt", "diffuser", "woodenpiece", "grain", "catcher", "snowman", "mansion", "spaghetti", "facemask", "slate", "peacock", "fiddled", "designer", "radiator", "speedlite", "old", "scrubber", "fenugreek", "optical", "scrub", "cloud", "soya", "mahjong", "caddy", "sprinkle", "blue", "pump", "knack", "earpiece", "gram", "faucet", "how", "flame", "mold", "lid", "driptip", "switchbox", "gasstove", "pillar", "lump", "stitch", "ed", "curry", "carpet", "movement", "party", "google", "pouch", "quiche", "ap", "footage", "terracotta", "a deck-chair", "pellet", "compact", "tour", "vase", "lamb", "stepstool", "inventor", "ramen", "gift", "serviette", "simba", "hero", "chase", "measurement", "superbly", "mousepad", "barrage", "turtleneck", "macro", "pusher", "vada", "folding", "helicopter", "sky", "tea", "caliber", "yippee", "heroic", "boardmaker", "shoelace", "homeboy", "mudguard", "hourglass", "emergency", "treasure", "wood", "telkomsel", "\u0430 bonbonniere", "check", "hindu", "brake", "lifting", "trashcan", "starter", "powerswitch", "clover", "infuser", "photoframe", "hazel", "count", "trunkhole", "command", "system", "clever", "flashlight", "female", "jalebis", "child", "house", "raft", "nutrition", "ziploc", "milk", "kiwi", "chandelier", "tangerine", "le", "barbie", "aim", "visiting", "sapodilla", "console", "hairclipper", "gassstove", "ointment", "eyeshadow", "clock", "sideboard", "mentions", "cologne", "reality", "artifacts", "cuppa", "pick", "dial", "pushing slightly", "diamond", "prayer", "quan", "repellent", "steering", "baseball", "formula", "hardcover", "mike", "sideview", "package", "salami", "gland", "planisphere", "stack", "carroll", "width", "scared", "center", "career", "leather", "tap", "a tiffin-box", "spexbox", "glue", "spanner", "papered", "squeegee", "strand", "brochure", "khaki", "soto", "coco", "serve", "file", "correction", "gel", "gnocchi", "beanbag", "pedal", "ketchup", "iphone", "k cup", "stapler", "schedule", "article", "it", "outdrink", "crow", "bok", "stock", "bandanna", "sealing", "graham", "pod", "kadam", "canola", "motion", "smoothie", "pebble", "handle", "peso", "poor", "handheld", "leo", "sideways", "blade", "face", "whisky", "animal", "quarter", "handsaw", "pastry", "bolster", "t-shirt", "jam-box", "luggage", "gent", "ludo", "a pouch", "mineshaft", "pikachu", "waterbottle", "aux", "head", "design", "lookie", "tablespoon", "sense", "marmot", "pottery", "mixergrinder", "platform", "bead", "harddisks", "oval", "highlight", "crayon", "sequence", "painter", "dualshock", "hotpot", "foot", "coursework", "candelholder", "stout", "condiment", "discount", "character", "celery", "pickles", "handy", "rib", "sketch", "thickness", "tassel", "lit", "supplement", "decorative", "tac", "tee", "cleansing", "chiller", "plush", "type", "corona", "cloth napkin", "granules", "bicycles", "brinjal", "mannequin", "flask", "bulb", "mile", "field", "play-doh", "leader", "guar", "shopping", "multipocket", "arrangement", "stethoscope", "fuel", "plasticbox", "amethyst", "boots", "micro", "meltykiss", "slushie", "gator", "chapel", "wrist-watch", "breastpin", "list", "marinade", "sat", "lego", "deo", "overboard", "globe", "yard", "teapot", "lady", "sneaker", "waller", "keychain", "rom", "greeting", "canister", "battery", "test", "instant", "bench", "antistress", "mattress", "number", "city", "peach", "timepiece", "oregano", "activation", "numberplate", "syringe", "saving", "quinoa", "thread", "padlock", "a whipping-top", "part", "encase", "salompas", "cordial", "ad", "mixer", "desktop", "lotiontube", "clipboard", "blocknote", "idol", "bismuth", "starbucks", "vos", "dumbbells", "alarm", "crumb", "treat", "necklace", "sun/moon", "gillette", "barstool", "rupee", "picture", "soapy", "flasdisk", "shameful", "soda", "bandage", "igniter", "paint", "inset", "foundation", "humidifier", "barbeque", "ointment-box", "webcam", "stable", "metallblock", "installation", "mung", "flor", "dabba", "crips", "bulldozer", "endives", "cartridge", "graph", "appointment", "the", "celeadoscope", "sandalwood", "stingray", "flash", "infinity", "float", "messenger", "trooper", "step", "timer", "atm", "percentage", "teeter", "coconut", "ostrich", "puppy", "propellers", "shredder", "drafted", "drinking", "headband", "breath", "screwdriver", "since", "kicker", "twisting", "cancel", "stomach", "rhododendron", "hairspray", "calcium", "carabinieri", "toast", "semen", "visit", "drug", "kennel", "plantain", "seal", "zip", "register", "scrap", "casino", "ciggeretts", "alebrije", "grater", "start", "cacao", "guava", "babypowder", "stuffto", "crock", "tube", "flashdisk", "myself", "goggles", "scrunchie", "poking", "sassing", "threshold", "exercise", "xbox", "aromatic", "agitator", "spool", "spiderman", "creditcard", "greensalad", "shaolin", "examination", "liver", "cig", "quentin", "plastic-container", "sheet", "hairpins", "rosemary", "kendall", "pine", "store", "lip", "art", "wardrobe", "bedsheet", "buttermilk", "locker", "hour", "tree", "an anti-perspirant", "cul", "row", "medication", "pumpkin", "toy-car", "bros", "tiara", "autorickshaw", "earbud", "lead", "kettle", "lung", "marker", "airplane", "himalayan", "let", "scope", "trophy", "poder", "real", "colouring", "batman", "matchstick", "sawdust", "race", "river", "koala", "earphone", "device", "chartpaper", "powdering", "ear", "tel", "siphon", "heater", "scenery", "ipod", "marries", "family", "ballast", "portfolio", "sox", "thief", "lever", "shoebox", "shine", "digital", "basin", "apricot", "playboy", "casa", "bottleflip", "liter", "label", "aid", "pit", "aluminum", "bowling", "firetruck", "bourgeois", "saver", "cheetos", "whetstone", "poloshirt", "visor", "displace", "garner", "straightened", "bulbsocket", "gold", "earthen", "boob", "soft q-tip", "doorbell", "pencilbox", "microwaveoven", "ciggerate", "skull", "oven", "cottoned", "bend", "yacht", "gauge", "replace", "reacting", "harmonica", "imac", "t-shir", "folding stocking", "perspiring", "leaflet", "freeze", "fibre", "grinding", "music", "syrup", "sofa", "switchboard", "feuerzeug", "philip", "a decorated can", "handkerchief", "tabula", "none", "sunglasses", "har", "production", "bic", "sound", "monkey", "hill", "clementine", "sword", "leaver", "spring", "lower", "regulator", "bottletop", "tulsa", "breaker", "toothbrush", "a cylindrical can", "microfiber", "rubberstamp", "caraway", "torch", "shell", "santaclaus", "door", "printer", "talc", "bookcase", "relay", "twister", "began", "highlighting", "libera", "push", "plucked", "higher", "brash", "stiffen", "jal", "dump", "sole", "sunflower", "extensor", "tequila", "hibiscus", "never", "batmobile", "dreidel", "finger", "gown", "hotspots", "scroll", "hands", "citrus", "pigtail", "machinery", "freshener", "star", "what", "sucker", "ginger", "primer", "autumn", "vine", "eggplant", "turtle", "cordless", "spray", "guitar", "basal", "fleshy", "oyster", "aniseed", "trafficlight", "safety", "hajji", "pitcher", "clockwatche", "biryani", "eye", "waste", "cassava", "display", "salons", "dictionary", "blow", "repressor", "space", "nectarine", "tylenol", "freshman's", "tinsel", "hat", "keg", "enchanter", "sambar", "crate", "sail", "laze", "platic", "a can", "marsh", "solution", "taco", "fly", "polythene", "bo", "eyeglass", "chick", "cicada", "shard", "shock", "dynamo", "hawaiian", "scooty", "shaft", "dove", "adjuster", "timewatch", "makerpen", "wok", "photostat", "chess", "bell", "sticky", "cooking", "peppermint", "vector", "scandal", "vegetablepears", "listener", "stylus", "dioxide", "setofcompasses", "billhook", "size", "towel", "sony", "rooster", "vegetable", "idle", "stirred", "mosquito", "repelled", "beyblade", "seat", "carjack", "diesel", "chili", "drain", "thin", "discgolf", "coffemix", "avocado", "slipper", "dab", "toothpaste", "landscape", "cardamom", "post", "masher", "powerpoint", "work", "bank", "changer", "dropper", "chunk", "kleenex", "stonewall", "camo", "syal", "strainer", "lipgloss", "cactus", "keyhanger", "road", "tablecloth", "papier", "lewis", "sainthood", "pincushion", "blind", "yo", "memo", "moisturiser", "computer", "polo", "puncher", "cookbook", "spec", "paprika", "cook", "phase", "tulle", "sculpture", "killed", "boomerang", "lamppost", "porridge", "dumb", "wheel", "lollipop", "decor", "access", "bush", "band", "firm", "flexometer", "hood", "me", "cluster", "we", "speedball", "rake", "cigeret", "topper", "drop", "business", "angel", "magnifying", "a k-cup", "a hand-kerchief", "braun", "jam", "look", "speaks", "mousetrap", "dentalpick", "charleston", "diner", "halo", "nutshell", "footwear", "teeth", "hamper", "microscope", "ocean", "pascal", "glasses", "a diary", "handicraft", "fez", "desert", "bullpen", "trash", "handlebar", "sun", "mona", "duvet", "bennie", "gym", "deadbolt", "pea", "tailpipe", "purple", "smashed", "pursue", "gooseberry", "odobenus", "adopted", "doggie", "carriage", "god", "rudraksh", "barrel", "silo", "wiper", "groundhog", "accumulator", "bicycle", "noise", "switched", "pud", "salty", "correspondence", "rearview", "telephone", "bureau", "grasshopper", "maze", "rat", "tom", "backcover", "coffin", "boat", "charging", "random", "frond", "voltage", "preserve", "diver", "maid", "dowel", "meth", "beanie", "drum", "chan", "moon", "batter", "barrette", "peeler", "scoop", "cd-rom", "burden", "tag", "meat", "fork", "fidget", "hawaii", "plan", "tool", "indofood", "nutella", "naphthalene", "sap", "lan", "softly", "risk", "pay", "ipad", "standard", "plugging", "tell", "cos", "joker", "clay", "trap", "cornet", "bra", "therein", "stiletto", "cabin", "duct", "mobile", "playing", "fidgetspinner", "keypad", "lip-care", "silicon", "titan", "a ukelele", "transfer", "medal", "tofu", "bubble", "abby", "cigarbutt", "cheese", "carbon", "bump", "canteen", "bac", "spoon", "conditioner", "xylophone", "tampon", "coating", "arm", "owl", "copen", "a lantern", "sniper", "washcloth", "plume", "hummus", "volt", "kernel", "kid", "roof", "class", "eyedrops", "trinket", "via", "junk", "case", "notecard", "ponzu", "kiosk", "henhouse", "comfort", "fours", "cleanser", "toot", "nothing", "fishing", "planter", "knee", "savoury", "cane", "stretchy", "chill", "dolphin", "button", "depressed", "wolverine", "maxwell", "downwards", "amrutanjan", "pashmina", "aiirbud", "garam", "right", "headline", "yeast", "plugpoint", "a bible", "army", "crossword", "gum", "attention", "upwards", "hen", "bouncer", "orange", "shield", "asbury", "lampshade", "kaugummi-packung", "chute", "roomfreshner", "taillight", "vinegar", "hoe", "plank", "whipper", "fiber", "fingernail", "pith", "photograph", "combine", "everready", "sinus", "imam", "lightning", "buffer", "thick", "wastebasket", "spirit", "feather falling", "hairbrush", "showerhead", "person", "cracker", "frame", "egg", "wet", "grape", "comb", "swamp", "gateway", "jelly", "mountain", "naan", "weave", "ratchet", "woollen", "skillet", "supper", "kita", "toiletseat", "rosmarus", "cabe", "troll", "print", "salve", "tissue", "henna", "pushing", "vegetation", "twitter", "plywood", "ship", "cleat", "granite", "trophies", "calculate", "softness", "toolbox", "rail", "camcorder", "coil", "sink", "keri", "flag", "pound", "cylinder", "crater", "moocakebox", "countryside", "body-lotion", "lotus", "facemasm", "wire", "buttons", "banister", "item", "crosswalk", "dark", "shall", "magnet", "bedsheets", "dumbbell", "salt", "water", "boot", "pet", "melatonin", "sharpness", "postcard", "fitting", "pompom", "speedometer", "trunk", "kiss", "meganthi", "medicine", "pastic", "bay", "hearing", "food", "a", "ca", "breadcrumb", "elephant", "stabillo", "tulip", "copybook", "something", "saint", "mobilephone", "stove", "skin", "turkey", "repellant", "torchlight", "rectangular", "india", "log", "adaptor", "dough", "ignition", "cardigan", "nugget", "closing", "military", "background", "bull", "whiskey", "an i.d.", "over", "bailed", "flavoring", "dumber", "sprayer", "blister", "under", "jogging", "swimmer", "baby", "vehicle", "day", "pong", "cookie", "nebulizer", "honda", "mood", "exact", "nova", "muffler", "garda", "maracas", "tupperware", "tide", "aroma", "garage", "snack", "treadmill", "flashdisks", "spectacular", "chakra", "tip", "sugar", "straw", "widmore", "gun", "elevator", "lightfire", "march", "baking", "pencil", "tomato", "highchair", "audio", "light", "nightlight", "narcissus", "blood", "escalator", "meet", "vitamin", "currency", "rift", "brow", "lamtoro", "hazelnut", "sandwiches", "wear", "cafe", "staircase", "popcan", "eagle", "composition", "lean", "suave", "reader", "skipping", "slurp", "radish", "darth", "mahal", "biro", "assembly", "broomstick", "porcelain", "mora", "cycling", "headscarf", "bluetooth", "nailpolishes", "divide", "pistachio", "altar", "brooch", "life", "pad", "source", "pain", "sliding", "cord", "dumdum", "document", "ring", "nailfile", "handpurse", "flow", "duck", "tubular", "twig", "activator", "gellar", "make", "spoke", "record", "circular", "sardine", "journal", "monopoly", "scorpion", "complain", "sealed", "mail", "led", "jello", "whites", "conch", "top", "mortar", "m&m", "middle", "gearbox", "booklet", "remotecontroll", "starfish", "suction", "butane", "fennel", "blu", "stamped", "mailbox", "lap", "credit", "jumpdrive", "tamil", "richard", "pocketbook", "plastic-paper", "jewelry", "soap", "2liter", "cot", "video", "bridge", "thiruvalluar", "magazine", "markerboard", "note", "rickshaw", "chop", "teapowder", "empty", "blender", "ladoo", "rotate", "thirteen", "poodle", "bodylotion", "reindeer", "figure", "melt", "dessert", "sleeper", "flyer", "shirt", "suds", "airport", "squeeze", "fame", "mint", "jewellery", "funnel", "magnate", "weedeater", "mm", "chip", "pork", "pot", "beverage", "petrol", "strawberry", "mob", "binocular", "mill", "a trashcan", "clog", "felt", "waffle", "patron", "clutches", "flour", "crisp", "feeding", "windshield", "taskpane", "detail", "bathrobe", "puppet", "petroleum", "presser", "going", "nighty", "pomegranate", "grid", "beam", "papaya", "saw", "spaceman", "dipper", "ice", "mark", "closet", "shaker", "raid", "silly putty", "up", "lake", "of", "filament", "spike", "sprite", "building", "sandal", "transistor", "matters", "absorber", "volley", "happens", "thermostat", "tapemeasure", "dvdcase", "hipflask", "antiperspirant", "dime", "wand", "enamel", "craft", "of elastic", "one", "windowsill", "template", "laminating", "slander", "a roll-on", "sludge", "hel", "robe", "latex", "mocha", "silverware", "sim", "iron", "ac", "bodyspray", "citronella", "diningroom", "clamp", "turnip", "crowbar", "scratch", "front", "a napkin falling", "machine", "grease", "proton", "showered", "spacial", "cut", "underpants", "trolley", "toiletpaper", "open", "painkiller", "compassion", "bow", "product", "soil", "fish", "ounce", "drumstick", "smartphone", "antique", "bond", "careless", "coriander", "sweet", "cajuput", "fresher", "cranberry", "pipecleaner", "hedge", "rivet", "fairy", "a needle", "giftbox", "stain", "abacus", "van", "soup", "hex", "plugged", "screwed lid", "harley", "thermocol", "sons", "rollerskate", "loop", "fairbanks", "volume", "alcohol", "leave", "chackpice", "cereal", "hate", "towelette", "hair-oil", "cigarettebox", "medicines", "crocodile", "tampa", "support", "bandana", "rainbow", "lee", "eeg", "award", "radio", "hydrocolor", "protestant", "holder", "disney", "an e-reader", "pepperoni", "lunch", "hose", "ribbon", "pressure", "cupholder", "rhino", "skyscraper", "blackboard", "replete", "toilet", "buzz", "android", "sung", "violin", "louse", "beach", "emory", "reflector", "shoestring", "decoder", "emery", "lemon", "pail", "encyclopedia", "ingredient", "toll", "gravy", "anvil", "carol", "orbiter", "clothespin", "a cosmetic", "tigress", "jet", "broccoli", "railway", "sticker", "a seive", "geometry", "binoculars", "sausages", "kindle", "paperclip", "fob", "caprisun", "cause", "antacid", "dal", "toiletry", "mein", "vodka", "liquidate", "mason", "cabinet", "ladybug", "veneer", "cream-case", "doll", "ale", "thumbnail", "moss", "reliever", "man", "nutcracker", "ceiling", "trailing", "lipbalm", "charge", "yak", "doorlock", "banknote", "enclosure", "garbage", "poster", "cigar", "arrive", "gas", "cart", "curd", "ting", "va", "cuff", "butter", "outer", "carrying", "puller", "blower", "flasdisks", "airconditioner", "bulletin", "zucchini", "colony", "coaster", "packaging", "lunchbox", "tongs", "till", "fort", "slab", "place", "snowflake", "ofan", "network", "disckgolf", "inbuilt", "landscaping", "bed", "bottlecover", "writing", "mental", "cradle", "press", "dawn", "a watercan", "hydrogen", "analog", "gloss", "cutlery", "either", "refresher", "massager", "tobacco", "sphere", "planet", "teabag", "hall", "jean", "sublight", "skittles", "bone", "date", "letter", "nipple", "wastebin", "blush", "bathtowel", "point", "deod0rant", "charcoal", "filling", "balloon", "gadget", "tinfoil", "yoda", "pond", "fluid", "bracelet", "bad", "evo", "wallclock", "packing", "dishwasher", "vapour", "flashdrive", "burial", "typewriter", "rug", "fortune", "poly", "channel", "be", "pack", "tall", "storm", "wheatgrass", "bamboo", "ga", "a nail-brush", "brown", "popsicle", "module", "weights", "dry", "ink", "perfume", "dairy", "close", "appliance", "shelve", "installer", "fiddlehead", "theopods", "fog", "vest", "school", "inside", "headsteamer", "timeline", "sister", "aqua", "war", "thing", "cajeput", "back", "tuner", "exterior", "chapati", "rifle", "truck", "grille", "nut", "bobby", "magnifier", "side", "medium", "pompoms", "johnson", "arnica", "seasoning", "park", "bird", "super", "clothclip", "joystick", "whiteboard", "exhaust", "nailcutter", "spends", "clapper", "income", "chickpea", "marking", "totter", "game", "separate", "flora", "gulab", "swab", "len", "parts", "plant", "bikini", "supporter", "slot", "chalkboard", "mario", "pendent", "cashier", "cappuccino", "sellotape", "harelip", "cabbie", "mash", "shrimp", "e-reader", "grey", "crab", "miranda", "schoolbag", "glycerin", "sachet", "health", "propeller", "fixture", "ski", "sack", "showpiece", "television", "ripping a little", "formation", "chattukam", "bleach", "liston", "brief", "sewer", "saliva", "notice", "bikeparking", "liner", "spider", "triangle", "shadow", "friend", "ziplock", "rabbit", "oilbottle", "darwaza", "rattan", "earrings", "silk", "sunshine", "massage", "shrub", "pinch", "layer", "hub", "input", "wheelchair", "filing", "biker", "openner", "terrier", "emblem", "bib", "pilachu", "brassiere", "pon", "mandolin", "gear", "internet", "fiona", "ladder", "avenue", "route", "rimmed", "matchbox", "train", "slim", "autoriksha", "bong", "bin", "mug", "word", "teabags", "mentor", "server", "chargeable", "per", "ironborn", "flushed", "dangling", "falling", "putty", "ridge", "pilot", "transformer", "punch", "homeopathy", "raincoat", "cricket", "rubin", "speck", "mirror", "peppershaker", "packet", "gomuthra", "a mobile similar to other", "flap", "sample", "proposes", "amps", "ajinomoto", "dealer", "caesium", "slicer", "branch", "tine", "nest", "controlled", "model", "thumb", "showcase", "handphone", "footswitch", "handful", "microwave", "with", "inlet", "projector", "harddisk", "pushup", "kalu", "corn", "remove", "hoop", "index", "heansead", "apartment", "breast", "pocketknife", "made", "filler", "posit", "couid", "touched", "pipe", "disc", "card", "voting", "farm", "coca", "arrow", "piano", "rose", "espresso", "candy", "guidebook", "music-player", "beef", "deeper", "checkbook", "hamburger", "description", "mole", "ver", "backwash", "tuna", "rocket", "bitter", "expanded", "dirty", "wind", "stationery", "teaspoon", "nourishment", "ponch", "grip", "videogame", "ironing", "others", "snuff", "platter", "pair", "cutter", "heart", "yarn", "earing", "purifier", "burn", "candleholder", "lotintube", "firearm", "cable", "sundae", "buy", "walnut", "snicker", "nacho", "aspects", "die", "mellow", "carom", "cocoa", "boy", "hexagon", "talky", "staple", "cherry", "binds", "shame", "stank", "comicbook", "season", "ledge", "twine", "makes", "burger", "set-square", "weight", "waterpik", "shovel", "sanitizer", "logbook", "shop", "hulk", "matchbook", "kin", "alligator", "powerbutton", "rider", "muff", "hollow", "shallow", "snake", "sweater", "glad", "toddler", "domino", "holdall", "notebook", "boxing", "sponge", "box", "mutton", "spic", "cup-sauccer", "carter", "recycling", "nutmeg", "jesus", "matches", "specsbox", "koolaid", "nasoclear", "conifer", "cellphone", "kitten", "earring", "dexter", "razor-blades", "blurry", "varnish", "canopy", "choker", "reckless", "headgear", "broom", "saree", "dip", "dishsoap", "stay", "ruin", "chalkpiece", "rasa", "mousse", "granola", "dooropner", "peanutbutter", "lettuce", "newsletter", "thong", "gen", "chief", "dress", "lotion", "did", "gotten", "eyeliner", "handler", "shoe", "muzzle", "claw", "crusher", "frits", "carrot", "winter", "amongst", "seltzer", "moving down", "rubies", "colander", "thimble", "alumni", "symbol", "talk", "injection", "ashtray", "fit", "wrap", "payback", "herb", "griddle", "rolling", "jon", "wasp", "moussaka", "raspberry", "code", "ot", "headlight", "pinecone", "predicament", "minion", "toilette", "king", "skewer", "left", "insulation", "toothpick", "canvas", "nicholas", "a screw-wrench", "plain", "pulse", "charger", "pully", "thermos", "chestnut", "stained", "bill", "stopl", "glove", "gaslight", "cardboard", "fairness", "square", "astor", "vas", "soccerball", "pepsodent", "ro", "bet", "aimless", "subscription", "plat", "root", "bert", "silencer", "pilots", "solar", "tub", "softdrinks", "converter", "gin", "v", "shaper", "neck", "easel", "sheridan", "nailclipper", "chapathi", "bike", "almond", "stoplight", "elmo", "extinguisher", "panty", "leafy", "aircraft", "weed", "pasta", "jute", "razor", "potpourri", "handwash", "stripe", "peephole", "airfreshner", "jalapeno", "rockstar", "indoor", "traffic", "tin", "chilli", "chutney", "michi", "trainer", "trimmer", "tara", "junkfood", "conan", "role", "launcher", "outcrop", "nipper", "take", "cloth", "hairnet", "jewel", "pajama", "drawer", "group", "short", "meant", "barbecue", "steamer", "flute", "patch", "vanity", "orchid", "pregnancy", "sugarcane", "frothing", "bathtub", "hydrant", "vent", "zelda", "white pebble", "melon", "concealer", "sleeve", "rate", "basket", "christmas", "soap-case", "prune", "grabber", "woodenbox", "duster", "hope", "engrave", "instruction", "gripped", "scientist", "plettrum", "league", "tire", "tender", "okra", "stainless", "station", "ground", "control", "ferrocerium", "trouser", "drained", "mine", "sandstone", "mica", "coloring", "storage", "underwire", "keeper", "bandaid", "racing", "lime", "clutch", "tiffany", "chewbacca", "cali", "shower", "candles", "diva", "bastille", "stalk", "spare", "cupcake", "math", "racquetball", "corkscrew", "undershirt", "tummy", "wheelbarrow", "knit", "freezer", "deposit", "bouncy", "somrthing", "haired", "vegetables", "asafoetida", "saucepan", "draw", "base", "fastener", "jig", "deodorizer", "discards", "rest", "moscow", "coffeemaker", "dust", "ponytail", "armchair", "release", "tropical", "trowel", "remover", "flip", "come", "bark", "shark", "woodchips", "lint", "stuff", "backlight", "turn", "eg", "mitts", "embrucation", "shear", "cymbal", "ruby", "nature", "pairing", "mist", "similar", "pentagon", "mitten", "cent", "parrot", "seldom", "gasket", "inked", "watch", "tyre", "penguin", "needle", "wax", "talkie", "cpu", "racket", "nightstand", "corrected", "security", "flooring", "io", "hemi", "workout", "lollypop", "accelerator", "stabilizer", "flipflop", "temple", "a olive", "compound", "title", "sajiku", "scissors", "barley", "lifter", "suitcase", "perimeter", "residing", "lottery", "mascara", "kaleidoscope", "footvalve", "groundnut", "flowerpot", "stair", "coke", "half", "snow", "main", "butterknife", "fossil", "periscope", "booking", "remedy", "marijuana", "soldering", "watering", "cabbage", "boiling", "cucumber", "cauliflower", "runner", "pen-drive", "pappy", "contact", "a top", "peanut", "laser", "watermelon", "skeleton", "coin", "jug", "diaper", "blackberry", "a t-shirt", "at", "pawn", "mom", "blazer", "handset", "male", "keyring", "cam", "curling", "lesson", "moonraker", "multivitamin", "boost", "coffee", "tumbler", "keep", "enjoin", "m&m`s", "a spray-paint can", "basil", "hindi", "clockwork", "fridge", "puff-box", "headache", "nose", "chapstick", "invitation", "key", "straighter", "tape", "tennis", "clothesline", "pole", "fruitcake", "egg-cup", "coupon", "change", "hand", "flintstone", "hinge", "pigeon", "cow", "yam", "rapper", "matter", "touch", "salsa", "ex", "multivamins", "surface", "outlet", "pram", "fisherman", "an olive", "calculator", "tile", "jacket", "perform", "pendant", "beetle", "audi", "soapbox", "bistro", "cork", "wash-basin", "maggie", "wrist", "chilies", "stick", "tiffinbox", "all", "washingmaschine", "nail", "rook", "bouquet", "dumptrucks", "wristlet", "hangar", "moneyto", "pledge", "jasmine", "bundle", "mix", "pin", "people", "belt", "yolk", "cashew", "donald", "wig", "car", "lion", "jewelery", "shipper", "action", "utility", "merci-packung", "marlboro", "mitt", "daikon", "calamari", "cement", "track", "dosage", "rouge", "player", "tear", "win", "compressor", "dry chilly", "vanilla", "popcorn", "bomb", "mango", "goal", "dirtbag", "textsufer", "hay", "agarbatti", "guard", "cheaper", "machete", "bag", "sling", "sarong", "ricecooker", "spin", "hook", "spread", "clip", "alone", "regulate", "queue", "pubic", "fountain", "ups", "banner", "best", "measuring", "scalpel", "shaver", "speed", "manual", "backseat", "cotter", "membersmark", "cinnamon", "pampers", "kari", "shelf", "tamale", "urn", "toiletcabin", "ben", "down", "lentils", "ruler", "crash", "hacksaw", "bootie", "cellotape", "stool", "edge", "clasp", "cardholder", "accessory", "silver", "tortoise", "bottlecap", "punching", "a flashdrive", "decoration", "madam", "escobar", "lot", "yellowbook", "gore", "dol", "flower", "tie", "counter", "samurai", "miniature", "hairball", "kill", "herald", "pillowcase", "hob", "steel", "walkie", "well", "cigarstub", "structure", "welcome", "necessary", "shade", "crucifix", "loafer", "mini", "donkey", "eyeball", "puzzle", "water-bottle", "rack", "hanger", "dye", "ware", "dishdrainer", "pant", "saddle", "ajar", "mask", "dick", "carrier", "toy-gun", "bindi", "cooler", "trigger", "deity", "dishwashing", "incense", "hardbound", "tabletop", "garland", "debit", "toy", "wash", "soy", "pendulum", "gallery", "spary", "basketball", "blouse", "spectalics", "firework", "flushvalve", "fevigum", "bogey", "she'd", "outboard", "cube", "cone", "smokey", "tweezers", "advent", "powder", "monument", "clipping", "floss", "gelatine", "skimmed", "ventilator", "workshop", "houseplant", "parcel", "goofballs", "thermogiant", "pinging", "npaperote", "tongue", "steelbox", "hotdog", "do", "collate", "splitter", "lifebuoy", "flu", "parsley", "high", "readymade", "hardest", "midair", "robot", "flex", "tablet", "irrigation", "noodle", "line", "jenna", "dishcloth", "strip", "piggyback", "wasabi", "accessories", "expo", "areola", "pill", "videogames", "drawing", "department", "anchor", "microphone", "collection", "little", "toothpicks", "joy", "boating", "bonbon", "cushion", "beige", "cantaloupe", "mouth", "football", "auditorium", "backdoor", "pecan", "photo", "cardreader", "walk", "blue nailpolish", "shed", "oscar", "cider", "muesli", "chain", "dashboard", "hanging", "dutch", "candlestick", "blows", "chapels", "dimmer", "term", "care", "paperweight", "organiser", "peg", "robin", "gamed", "waist", "film", "peroxide", "idly", "spill", "neem", "reel", "potato", "pop", "stepped", "multiple", "stereo", "indicator", "tote", "sweety", "data", "rule", "bit", "toggle", "saltshaker", "gong", "percent", "throat", "mala", "flavor", "statue", "dirt", "velvet", "lentil", "shoot", "distribution", "fuck", "antiseptic", "multicolored", "stand", "ram", "carton", "ethernet", "wish", "lay", "ration", "inhaler", "halloween", "receiver", "boxes", "pimento", "worm", "fluff", "kara", "fix", "recliner", "shotglass", "resin", "nailpolish", "bristle", "avoids", "started", "watercontainer", "factory", "bitten", "spice", "makeup", "whitener", "milkmaid", "pate", "detector", "power", "not", "crust", "adapter", "shuttle", "omelette", "everyday", "crop", "fold", "phone", "sock", "butt", "thermo", "bobbin", "toaster", "petulant", "choke", "joint", "stop", "a short", "spark", "calender", "dosa", "snusdisk", "or", "tablet-box", "keyword", "dish", "auto", "block", "elbow", "someone", "chisel", "owen", "wristband", "object", "walker", "heating", "morten", "tail", "cob", "mummy", "knick", "forget-me-nots", "sign", "saucer", "wollen", "kay", "whisk", "potty", "mayonnaise", "too", "pier", "tent", "dog", "waterless", "rich", "generator", "tumble", "a pebble", "cosmetic", "pug", "srikaya", "demolition", "camphor", "wrapper", "eyecurler", "breakfast", "para", "vial", "mustache", "chappathi", "pane", "stroller", "gait", "compass-box", "remote-control", "starburst", "peep", "paintbrush", "witch", "crackpot", "bar", "tab", "wolf", "teddy", "grocery", "folder", "cockroach", "toe", "plunger", "gallon", "balcony", "smith", "marble", "earbuds", "atomizer", "biscuit", "casing", "honey", "ottoman", "foster", "sex", "moment", "bald", "men", "datta", "hula", "goring", "foil", "palm", "lose", "length", "pas", "staff", "anti", "topless", "flip-flop", "giftpack", "plantpot", "armrest", "circle", "chap", "beet", "textile", "earth", "seatbelt", "cameraman", "dart", "e-cigarette", "icecream", "radiation", "sal", "penstand", "chopstick", "watercolor", "direction", "kneeled", "fingerboard", "vader", "hello", "riffle", "digger", "son", "bingo", "photographer", "inner", "vessel", "mafroom", "mud", "salad", "grinder", "bathroom", "figurine", "pieces", "foosball", "charmander", "mach", "chest", "raises", "jump", "garden", "icepack", "bacterium", "fevikwik", "seagrass", "octopus", "corner", "robbing", "nickel", "fist", "meal", "screwup", "maker", "scorer", "unit", "electricity", "jackfruit", "alkaline", "caterpillar", "rugby", "bunch", "exam", "cigarettes", "tempeh", "advisement", "videocard", "pe", "bee", "dipstick", "adhesive", "paperroll", "apparatus", "pretending", "swap", "measure", "cupboard", "wreath", "rubber", "sunglass", "croissant", "steer", "token", "pinafore", "polystyrene", "hippopotamus", "dining", "flannel", "bawl", "bible", "canderelbox", "musicsheet", "palace", "taboo", "scratching", "lighting", "unchain", "aquarium", "mp3", "tung", "curler", "oreo", "happiness", "colour", "booster", "wound", "grams", "jaggery", "in", "samosa", "pickle", "pixie", "pita", "kob", "deer", "she", "rim", "mineral", "hershey", "amusement", "facebook", "potholes", "scream", "chenille", "tattoo", "hairfastener", "pig", "vape", "cayenne", "ceramic", "fruit", "pure", "fenceweave", "catnip", "keledeoscope", "easter", "sunscreen", "yoghurt", "logo", "pepertowel", "beater", "frock", "milkshake", "fabric", "envelope", "gate", "polenta", "textbook", "kerchief", "compass", "whirlpool", "coat", "handtowel", "skywalker", "driller", "connection", "paid", "sagebrush", "sport", "seaweed", "tiffenbox", "boxer", "electro", "pencilcase", "locket", "plum", "sandwich", "bolt", "tray", "slide", "agarbathi", "velcro", "warm", "tic-tacs", "excel", "striker", "greenery", "trailer", "pom", "pirate", "mosque", "com", "pool", "content", "birthday", "aftershave", "cub", "bitterguard", "parachute", "loc", "topside", "underwear with other underwear", "advertisement", "implement", "tiffin", "greyhound", "ballpoint", "powerplug", "a thermous", "cup", "burning", "fingerprint", "gi", "thermal", "tack", "fat", "anbesol", "lipstick", "drying", "wineglass", "webcamera", "backpack", "enter", "brush", "surf", "leash", "pillbox", "softball", "router", "anklet", "port", "burner", "piggy", "glow", "glucose", "entertainment", "whiter", "airliner", "firebox", "see", "capacitor", "seed", "valve", "seating", "minnie", "mid", "nurse", "ladle", "sidewalk", "brushed", "headphones", "taj", "pretzel", "railing", "job", "sandals", "puffin", "mongoose", "gravel", "license", "paperback", "dot", "plate", "ready", "resistance", "rubber-sheet", "zipper", "coffeemix", "cats", "remote", "takeout", "starch", "custard", "pinestraw", "iris", "strap", "biriyani", "table", "pendriver", "an ice-cream", "john", "bearing", "papertowel", "election", "museum", "onions", "carry", "etc", "culture", "nasa", "mixture", "acorn", "dinner", "phonecall", "cinderblock", "lift", "sauce", "chockpiece", "between", "quill", "shelter", "rattle", "refill", "toner", "swing", "speakerphone", "receptacle", "yu", "panel", "lace", "embroidery", "handtowels", "fire", "bullet", "a ukulele", "taperecorder", "fault", "news", "string", "electabuzz", "paste", "rind", "numeric", "papers", "a comic", "cutting", "steelglass", "gorilla", "remotecontroler", "snap", "bronze", "choice", "clothes", "opener", "shellac", "pudding", "dryer", "spillikin", "shallot", "cufflink", "style", "pen", "yoyo", "fluorescent", "bimbariner", "heap", "stacking", "one of many similar", "knot", "moose", "dhoti", "mope", "paper", "chord", "conjuring", "tandem", "handwasher", "beetroot", "processor", "prototype", "dumpster", "seashell", "doraemon", "dustbin", "bacon", "use", "carrots", "eraser", "spun", "cookingpot", "ducky", "container", "electronics", "moisturizer", "slippers", "odor", "receive", "flossed", "elastic", "frisbee", "kitchen", "scissor", "sand", "bon", "coversheet", "cookies", "spectacle", "squirrel", "discard", "tamper", "q-tip", "twin", "carafe", "dresser", "drone", "cool", "dream", "os", "cuttingboard", "wise", "photocopier", "plaster", "kollatta", "verified", "lock", "he", "laminated", "bomber", "cleaver", "pile", "pa", "tortilla", "hockey", "footrace", "garlic", "liquid", "tabasco", "the can", "leg", "suit", "kitty", "jell", "aerosol", "aloe", "spade", "kangaroo", "catch", "smoke", "tipex-maus", "science", "chalk", "sesame", "battleship", "dollar", "goofball", "videocamera", "margarine", "twist", "venom", "outdoor", "terrarium", "tapioca", "sol", "bookmark", "\u00e7oins", "triple", "mesh", "pistol", "pear", "vapor", "mouthwash", "glade", "bitumen", "shaving", "keying", "oh", "club", "crystal", "page", "acetone", "scoured", "pull", "hole", "speaker", "tripod", "mainswitch", "camera", "atta", "rajah", "tomatillo", "textmarker", "metal", "papa", "brace", "boa", "tether", "chatgerlight", "tired", "swan", "claus", "recipient", "cap", "blanket", "sea", "church", "spirometer", "vicks", "radioclock", "wooden", "pumper", "skateboard", "lychee", "knight", "wristwatch", "scooter", "truth", "vinyl", "buff", "fireplace", "fox", "limestone", "countertop", "headphoneplug", "wheat", "cassette", "shampoo", "lamp", "watt", "drink", "origami", "steak", "link", "headlamp", "rope", "zebra", "socket", "fall", "disk", "flush", "time", "lasered", "aircondition", "cellophane", "cannon", "bean", "bucket", "ads", "sunset", "chocolate", "paraffin", "lightweight spackling", "oatmealbox", "downy", "plug", "batteries", "jealousies", "litter", "groudnut", "cleaning", "pencils", "compression", "union", "attempted", "loader", "skirt", "town", "hair-pin", "headphone", "gumbo", "lightbulb", "selfie", "placemat", "buckle", "chock", "poorest", "gluestick", "candelabra", "fleece", "textsurfer", "polisher", "tennisball", "immersion", "cello", "multi", "lawn", "pyramid", "plastic", "roller", "vaseline", "headset", "powered", "travelling", "bug", "daisy", "recon", "level", "cooldrink", "whale", "a mobile", "roulette", "rosary", "cash", "teashirt", "trivet", "shutter", "picker", "goddess", "receiptment", "chat", "a nailpolish", "washer", "sugarholder", "text", "lens", "bonnet", "broken", "parking", "voice", "hairdryer", "elles", "vera", "clove", "rod", "grill", "vamos", "joon", "series", "pie", "format", "superman", "latte", "fuse", "pringles", "squishy", "axe", "mantis", "lacquer", "shitbox", "pan", "catalog", "still", "puddy", "transparent", "cola", "highlander", "ply", "font", "lowercase", "recline", "underwear", "running", "nailclippers", "insulator", "scarf", "maple", "fragment", "latch", "pancake", "krishna", "sandpaper", "schokolade", "bookstand", "grate", "cheerio", "dome", "injector", "martini", "world", "fevicol", "ailment", "stab", "mccarthy", "smiley", "firewood", "redpen", "feather", "mobile-cover", "planner", "offset", "glass", "movie", "exit", "writer", "rubbish", "flywheel", "donit", "po", "crumbles", "from", "juicer", "swat", "beholder", "washing", "copper", "organizer", "abs", "master", "pesto", "carmen", "pretend", "drip", "self", "arousal", "cartoon", "jumper", "lava", "eave", "diskette", "lantern", "a q-tip", "air", "tics", "tum", "beaker", "shoo", "'tube", "ghee", "mushroom", "cream", "thea", "thumbtack", "hemp", "changing", "wad", "screen", "crockery", "poly-bag", "marilyn", "taro", "bass", "chou", "bland", "mit", "nailpaint", "compartment", "utensils", "tej", "neon", "memory", "cross", "beans", "foal", "gauze", "fashion", "closure", "silicone", "sofdrinks", "standing", "big", "paperboy", "id", "baton", "panda", "asparagus", "millet", "study", "freeduino", "epsom", "bottle", "juice", "dinosaur", "met", "gem", "a yo-yo", "rubberband", "beauty", "passport", "kolatta", "a rose", "wreckage", "killer", "drainage", "oscillograph", "household", "scotch", "lemonade", "handsfree", "bugle", "kamal", "lizard", "chimney", "sucked", "fine", "delight", "post-it", "badminton", "entrance", "bricheta", "phonebook", "forehead", "furniture", "mama", "element", "eyebrow", "absorbent", "valentina", "inmost", "bud", "wallframe", "sill", "handcream", "office", "donut", "way", "voucher", "tipp-ex", "raggedy", "book", "stress", "vise", "mate", "valentine", "boardmarker", "fizz", "husband", "budweiser", "grab", "drag", "pincer", "citron", "land", "blue stuffed bear", "porch", "connector", "denim", "marmalade", "so", "night", "tough", "nob", "break", "disinfectant", "dock", "stew", "signal", "sac", "helm", "handicap", "novel", "masking", "notepad", "matchup", "supply", "mulch", "tower", "sweetener", "wine", "hansaplast", "spinning", "bricks", "identity", "thine", "bungee", "roti", "nylon", "coinpurse", "crutch", "yardstick", "linoleum", "earplugs", "floor", "cel", "grave", "bam", "ifl", "creme", "cottontail", "handrail", "prong", "terminal", "banana", "end", "the pouch", "instructive", "mural", "menthol", "wireless", "yogurt", "napkin", "umbrellas", "jewels", "wattertank", "glittery", "shave", "adama", "dragon", "gatsby", "reflection", "kind", "cough", "image", "stovetop", "cooked", "jeep", "pasties", "ingot", "palette", "frying", "blast", "desk", "cape", "lush", "tinky", "electrician", "pensive", "good", "multiplayer", "tooth", "sharpie", "kite", "bottom", "bowl", "wallet", "normal", "motor", "down a pen", "styrofoam", "creamer", "roadside", "sushi", "wool", "capsule", "lesions", "love", "de", "angler", "coach", "scalp", "woolen", "aluminium", "blushed", "penny", "confetti", "aeroplane", "install", "wast", "bab", "a vegetable", "eyelash", "a puppy", "firecracker", "chem", "hotchpotch", "gourd", "thorn", "extension", "erase", "flintstones", "piece", "lavender", "ball", "fallout", "mousebad", "rosebud", "shoehorn", "ironed", "lied", "damn", "poker", "homos", "alphabet", "laptop", "protector", "dispenser", "contained", "petal", "smudge", "falcon", "cage", "turmeric", "slider", "la", "shoulder", "keyser", "bowel", "eskimo", "dad", "r2d2", "tester", "hulahoops", "glitter", "santa", "director", "grass", "genie", "oil", "stone", "mod", "upside", "doom", "stake", "rain", "california", "keurrig", "cooker", "cat", "polish", "extractor", "redsalad", "candle-bottle", "switch", "puffed", "hotel", "orangepeel", "can", "flyswatter", "coffe", "ofther", "loot", "visors", "usb-stick", "excavator", "painting", "crane", "marshmallow", "royal", "bath", "grommet", "butterfly", "vino", "library", "dandelion", "can't", "grader", "nano", "backing", "flatscreen", "utensil", "pickaxe", "construction", "bodywash", "map", "zero", "operating", "doorhandle", "ab", "nice", "peel", "buddha", "procure", "board", "stumped", "locking", "pamphlet", "mallet", "sheep", "lure", "stuffed", "jack", "prenjak", "slip", "spindle", "dagger", "tot", "column", "capo", "cheque", "manga", "flop", "collector", "crapola", "attachment", "onion", "rice", "davidson", "bowtie", "swizzle", "rock", "slime", "gatorade", "quick", "weel", "doormat", "a remote", "usb", "chamber", "nerf", "pepper", "farmer", "apple", "sharpener", "drill", "bedroom", "swatter", "safe", "underline", "scent", "fladhdisk", "veg", "candle", "octagon", "crown", "tips", "pillow", "mustard", "flipcover", "casserole", "wall", "ornithopod", "electricbox", "plasticbag", "cubby", "eatable", "pestle", "guide", "hardware", "husk", "monitor", "stein", "pepsi", "hearth", "mechanism", "cassettes", "malice", "brick", "notizheft", "mandarin", "goat", "hairclips", "shot", "bankbook", "tread", "cycle", "bear", "rein", "i", "camel", "snowball", "lighter", "magic", "newsstand", "flashcards", "hut", "shawl", "harvester", "highlighter", "advertising", "green chilly", "interior", "anteroom", "baggie", "creeper", "story", "rag", "section", "coup", "globules", "deodorant", "handgun", "chew", "bat", "silica", "filter", "talcum", "chewing", "snowglobe", "island", "fig", "shifu", "reveille", "raisin", "mantle", "dishtowel", "soul", "serving", "lawnmower", "tint", "harp", "stamp", "bingbang", "poseidon", "recorder", "shiva", "prism", "angrybird", "pamper", "panorama", "stem", "company", "tata", "hanky", "deal", "energy", "create", "stucco", "based", "washbasin", "fry", "adult", "flake", "extended", "fatty", "ilk", "divider", "tailor", "energon", "rust", "reading", "coffeepot", "snail", "mac", "playground", "stud", "sari", "paddle", "0,10\u20ac", "maroon", "statuette", "spot", "plastic-cover", "jawbone", "jar", "agent", "view", "necktie", "sage", "mellows", "antenna", "swiss-knife", "newsprint", "chair", "pattern", "bookshelf", "partenon", "sausage", "clothe", "fil", "launder", "choco", "junction", "receipt", "service", "steam", "umbrella", "comp", "champagne", "oat", "teeshirt", "signboard", "heel", "sitch", "giraffe", "ticket", "holster", "loofah", "lanyard", "peak", "loaf", "hotbox", "mouthpiece", "glassholder", "bun", "put", "name", "hoodie", "handspinner", "pocket", "lincoln", "oath", "calligraphy", "bran", "owner", "fei", "motorcycle", "match", "envelop", "matt", "peace", "tank", "tidy", "bot", "tiger", "lactose", "spinner", "dell", "scanner", "a nose", "stones", "keywords", "whistle", "stung", "ant", "crochet", "ornament", "driver", "gotta", "set", "inkfiller", "home", "water-can", "nutrijel", "software", "drinker", "shuttlecock", "pearl", "briefcase", "dreamcatcher", "chart", "tamarind", "votive", "define", "winner", "net", "web", "rub", "lorry", "chatter", "couch", "sieve", "squeezer", "cooped", "suki", "bedding", "condom", "soybean", "bathing", "tootsie", "a elastic", "bowler", "sandbox", "form", "modem", "sloping", "sugarcoat", "minor", "paper-board", "sterno", "nasal", "knife", "pink", "teletubbies", "thermometer", "heather", "your", "bus", "inboard", "gruel", "admiral", "mandala", "stacker", "stopper", "skate", "alpenliebe", "10\u20ac", "relief", "album", "kota", "goodnight", "lo", "wing", "stabiliser", "clipper", "dummy", "barometer", "condensation", "cigarette", "pic", "iguana", "inverter", "tong", "sweeper", "wheeler", "handout", "instrument", "nylon-bag", "thank", "market", "dada", "lam", "bunny", "eco", "creamcup", "solder", "mobil", "note-book", "wafer", "us", "getup", "staples", "ache", "pedicure", "liquor", "lightningbulb", "slinky", "cumin", "optic", "moisturizing", "shrek", "feeder", "meter", "athe", "playstation", "trident", "watercan", "restaurant", "doily", "spinach", "tetrapack", "prescription", "lord", "re", "cock", "olive", "dartboard", "cover", "pint", "claro", "mower", "millimeter", "masala", "spoil", "mop", "area", "pineapple", "winky", "pizza", "wipe", "haircomb", "woman", "cleaner", "leggings", "childrens", "chef", "dare", "chicken", "melodic", "gummy", "presume", "curtain", "calendar", "cell", "pointer", "six", "wedge", "pinwheel", "couple", "pencil-pouch", "hairpin", "carving", "muscle", "amplifier", "shakespeare", "surge", "colored", "show", "muffin", "contain", "wrapped", "sewing", "tonic", "ranch", "barely", "soccer", "ping", "wicker", "pricetag", "price", "docket", "bubblegum", "malaysia", "cake", "a post-it", "tongue-cleaner", "fragrance", "waterboard", "oatmeal", "body", "split", "component", "forget", "girl", "arthur", "powerball", "collar", "lavandin", "toffee", "sharper", "tub/container", "mess", "puto", "coffeecup", "move", "shape", "tarpaulin", "kadhakali", "majid", "menu", "foam", "smile", "doorknob", "room", "clothed", "dice", "copy", "vacuum", "gain", "tater", "boll", "fur", "saran", "ash", "stockpot", "screw", "forest", "bulge", "pangolin", "perforated", "goblet", "softener", "engine", "dustpan", "sewerage", "matrioska", "\\'' paper\\''fall\\''down", "pomade", "stripper", "trey", "soupbowl", "computermaus", "argue", "horlicks", "nickname", "eyehook", "human", "dew", "sniffer", "keyboard", "crisper", "radha", "birdcage", "crib", "lira", "doh", "detergent", "color", "play", "diary", "jetpack", "drive", "calf", "popper", "magician", "slice", "material", "laundry", "tractor", "pantry", "sander", "travel", "recipe", "cute", "odd", "landline", "waterhole", "handbag", "knob", "bread", "moist", "chilly", "scooper", "triangular", "pocahontas", "round", "fancy", "non", "cady", "fence", "portrait", "eiffel", "hammer", "induction", "refrigerator", "circuit", "stole", "scale", "mp3 casing", "manila", "span", "bangle", "insert", "helmet", "play-do", "golf", "mouthguard", "mic", "nozzle", "quilt", "controller", "sickle", "sale", "cringe", "clothing", "plane", "squash", "to", "starters", "frog", "horn", "kinder", "teacup", "brandy", "fan", "binder", "click", "recant", "mat", "shockubsorber", "nair", "chimpanzee", "keyhole", "batch", "cop", "search", "kit", "newspaper", "mouse", "gangsta", "team", "morning", "trip", "money", "brass", "pacifier", "white out", "usc", "roll", "yellow", "setsquare", "nonstick", "manicure", "status", "gamepieces", "vending", "frank", "pulp", "cocoon", "mixed", "violet", "chime", "papadum", "deck", "flowerwise", "teddybear", "purse", "bacteria", "insect", "post-il", "videotape", "wifi", "song", "say", "fluffy", "amp", "motorbike", "nappy", "halve", "hair", "concrete", "bouncing", "yoga"], "list_classes_train_verb": ["throw", "tilting", "stops", "stacking", "deflected", "burying", "pushing", "fall", "does", "approaching", "poke", "spilling", "come", "stuffing", "glide", "failing", "turn", "tearing", "be", "slides", "wipe", "spinning", "wiping", "bending", "drop", "close", "squeezing", "is", "bend", "removing", "sprinkle", "something", "starts", "stretched", "throwing", "piling", "closing", "wringing", "covering", "fit", "open", "move", "rolling", "moves", "stays", "left", "overflows", "folding", "gets", "digging", "dropping", "attach", "collide", "scoop", "collapsing", "support", "pretending", "missing", "lifting", "opening", "spins", "plugging", "trying", "deforms", "comes", "put", "colliding", "holding", "laying", "filming", "catching", "putting", "picking", "moving", "pass", "falling", "scooping", "sliding", "twisting", "stick", "pouring", "showing", "separates", "pick", "take", "revealing", "twist", "uncovering", "hitting", "tipping", "rolls", "poking", "slide", "stand", "are", "being", "spills", "remove", "right", "continues", "pour", "roll", "supported", "spread", "turning", "breaks", "sprinkling", "attaching", "squeeze", "falls", "pulling", "letting", "taking", "touching"], "list_classes_test_noun": ["a tooth-stick", "beer", "sweat", "fax", "spatula", "buffalo", "wrench", "brownie", "badge", "astray", "balm", "cotton", "miller", "tourist", "horse", "puff", "plastic-box", "mitersaw", "marigold", "talkto", "castle", "monster", "upper", "leaf", "sheath", "feed", "dangle", "window", "burrito", "sweatshirt", "grain", "catcher", "flatbread", "snowman", "spaghetti", "facemask", "slate", "peacock", "designer", "mutter", "knitting", "combination", "radiator", "wastepaper", "scrubber", "optical", "fenugreek", "scrub", "meatball", "cloud", "hold", "tonsil", "soya", "mahjong", "caddy", "blue", "pump", "gram", "faucet", "earpiece", "flame", "mold", "lid", "switchbox", "gasstove", "england", "pillar", "reptile", "curry", "carpet", "party", "pouch", "footage", "lepidium", "permanent", "compact", "vase", "lamb", "inventor", "ramen", "gift", "superbly", "measurement", "mousepad", "macro", "pusher", "helicopter", "tea", "caliber", "yippee", "heroic", "shoelace", "homeboy", "motorola", "mudguard", "laugh", "renault", "hourglass", "emergency", "treasure", "wood", "telkomsel", "check", "brake", "torture", "three", "starter", "trashcan", "infuser", "stickglue", "hazel", "stretch", "system", "flashlight", "jalebis", "child", "house", "nutrition", "milk", "kiwi", "chandelier", "tangerine", "barbie", "aim", "poll", "console", "hairclipper", "ointment", "eyeshadow", "clock", "mentions", "semolina", "cologne", "buck", "pick", "dial", "latin", "prayer", "repellent", "steering", "baseball", "formula", "hardcover", "package", "salami", "stack", "su", "sweatpants", "width", "center", "leather", "tap", "glue", "spanner", "brochure", "khaki", "coco", "washingmechine", "file", "guitarist", "correction", "handsome", "gel", "birdie", "rise", "pedal", "beanbag", "ketchup", "iphone", "stapler", "it", "article", "crow", "harder", "stock", "canola", "sealing", "pod", "graham", "duppatta", "kadam", "pebble", "handle", "peso", "poor", "handheld", "much", "blade", "face", "whisky", "lover", "animal", "habit", "quarter", "pastry", "bolster", "handsaw", "t-shirt", "pleat", "jam-box", "gent", "luggage", "baggage", "a pouch", "ludo", "dinette", "mineshaft", "pikachu", "waterbottle", "aux", "head", "tablespoon", "nailcutters", "sense", "pottery", "stopwatch", "bead", "highlight", "crayon", "sequence", "credential", "foot", "plastic-board", "condiment", "charity", "discount", "pickles", "incandescent", "catalogue", "sketch", "turning upside down", "lit", "decorative", "supplement", "weighed", "tac", "tee", "granules", "cleansing", "plush", "type", "grounndnut", "brinjal", "flask", "bulb", "irrigationsystem", "metre", "shopping", "arrangement", "stethoscope", "fuel", "raper", "micro", "slushie", "gator", "chapel", "wrist-watch", "breastpin", "startpack", "lego", "deo", "overboard", "globe", "intercom", "teapot", "lady", "sneaker", "keychain", "rom", "canister", "battery", "bench", "instant", "number", "city", "mattress", "peach", "numberplate", "oregano", "saving", "timepiece", "syringe", "thread", "padlock", "part", "encase", "splotch", "ad", "mixer", "desktop", "lotiontube", "clipboard", "idol", "bismuth", "rabbi", "alarm", "crumb", "luck", "smoking", "treat", "necklace", "recycle", "gillette", "barstool", "rupee", "an i.d", "picture", "one t-shirt to another t-shirts", "soapy", "flasdisk", "ballet", "soda", "bandage", "igniter", "paint", "rotor", "foundation", "inset", "want", "timeturner", "webcam", "stable", "organza", "installation", "a-tshirt", "cartridge", "graph", "sandalwood", "flash", "infinity", "messenger", "drape", "woodrow", "trooper", "step", "timer", "atm", "nyc green fingernail.com", "coconut", "puppy", "shredder", "drinking", "headband", "screwdriver", "twisting", "stomach", "hairspray", "carabinieri", "toast", "target", "drug", "synthetics", "kennel", "seal", "zip", "register", "scrap", "grater", "start", "guava", "babypowder", "crock", "tube", "flashdisk", "myself", "goggles", "sassing", "exercise", "xbox", "agitator", "aromatic", "pooh", "spool", "spiderman", "creditcard", "liver", "shaolin", "anothe", "quentin", "plastic-container", "sheet", "major", "hairpins", "kendall", "pine", "lip", "recover", "art", "wardrobe", "bedsheet", "coal", "quarry", "locker", "tree", "hour", "ponytailholder", "medication", "pumpkin", "toy-car", "nair", "tiara", "autorickshaw", "lead", "kettle", "marker", "airplane", "himalayan", "scope", "trophy", "opening", "bittergourd", "colouring", "batman", "matchstick", "race", "heft", "roasting", "river", "ear", "earphone", "device", "powdering", "koala", "pokemon", "heater", "scenery", "ipod", "family", "green", "thief", "lever", "shoebox", "shine", "digital", "basin", "clear", "playboy", "apricot", "casa", "wake", "liter", "label", "aid", "aluminum", "bowling", "jeweler", "eyepiece", "whetstone", "visor", "garner", "earthen", "gold", "range", "firebug", "soft q-tip", "pencilbox", "applesauce", "ciggerate", "skull", "oven", "cottoned", "bend", "yacht", "reacting", "harmonica", "leaflet", "music", "sofa", "switchboard", "syrup", "carburetor", "philip", "organ", "handkerchief", "tabula", "bic", "sound", "monkey", "clementine", "hill", "sword", "spring", "lower", "regulator", "bottletop", "seek", "toothbrush", "microfiber", "rubberstamp", "torch", "shell", "door", "printer", "bookcase", "talc", "filet", "glassbird", "push", "collide", "plucked", "protection", "pika", "sheriff", "caulk", "dump", "stiffen", "jal", "sole", "castor", "hibiscus", "memorabilia", "jujube", "dreidel", "finger", "scroll", "citrus", "machinery", "pigtail", "freshener", "star", "parathas", "sucker", "ginger", "primer", "alma", "eggplant", "turtle", "cordless", "spray", "guitar", "frisky", "safety", "pitcher", "biryani", "eye", "waste", "q-tips", "display", "dictionary", "blow", "repressor", "space", "nectarine", "hat", "nature", "enchanter", "sambar", "crate", "a can", "marsh", "solution", "fly", "polythene", "eyeglass", "chick", "cicada", "guy", "hawaiian", "shock", "dynamo", "scooty", "dove", "eardropper", "wok", "rum", "photostat", "chess", "bell", "sticky", "flax", "promise", "cooking", "peppermint", "scandal", "listener", "stylus", "dioxide", "setofcompasses", "shampoos", "towel", "sony", "rooster", "vegetable", "bengal", "vaporizer", "mosquito", "chewing-gum", "seat", "chili", "drain", "coffemix", "avocado", "clicker", "slipper", "dab", "toothpaste", "landscape", "cardamom", "post", "masher", "work", "bank", "dropper", "kleenex", "dancer", "camo", "whip", "strainer", "campus", "tinker", "cactus", "road", "tablecloth", "papier", "sainthood", "pincushion", "blind", "moisturiser", "computer", "mister", "polo", "puncher", "cookbook", "spec", "paprika", "cook", "axel", "sculpture", "boomerang", "dumb", "visitingcards", "wheel", "knickknack", "rippers", "sweatbox", "lollipop", "decor", "access", "bush", "band", "hood", "firm", "we", "cluster", "me", "rake", "drop", "submit", "business", "angel", "a k-cup", "magnifying", "a hand-kerchief", "jam", "repent", "speaks", "charleston", "nutshell", "footwear", "microscope", "hamper", "teeth", "barb", "glasses", "a diary", "handicraft", "minibar", "bullpen", "trash", "sun", "bennie", "gym", "deadbolt", "pea", "purple", "tailpipe", "smashed", "footballs", "pursue", "gooseberry", "'purse", "adopted", "doggie", "god", "wiper", "bicycle", "switched", "salty", "rearview", "telephone", "bureau", "hide", "tom", "rat", "backcover", "been", "coffin", "singer", "boat", "charging", "voltage", "preserve", "maid", "meth", "beanie", "drum", "chan", "comforter", "moon", "batter", "barrette", "peeler", "scoop", "'bedsheet", "tag", "drums", "meat", "fork", "fidget", "hawaii", "tool", "message", "nutella", "lan", "softly", "risk", "duffel", "ipad", "tell", "a w", "clay", "trap", "bra", "therein", "cabin", "fidgetspinner", "mobile", "duct", "lip-care", "playing", "keypad", "silicon", "titan", "transfer", "legiyam", "medal", "tofu", "bubble", "abby", "carbon", "cheese", "bump", "canteen", "spoon", "conditioner", "xylophone", "tampon", "arm", "owl", "betel", "a lantern", "washcloth", "hummus", "kernel", "kid", "roof", "class", "4", "trinket", "try", "caution", "via", "junk", "mickey", "case", "ponzu", "notecard", "comfort", "separator", "aide", "nothing", "fishing", "knee", "grassfeather", "liam", "cane", "chill", "button", "late", "crayons", "downwards", "ramp", "amrutanjan", "right", "headline", "cardvalidator", "spraypaint", "a bible", "army", "tape-roll", "gum", "attention", "tricycle", "orange", "shield", "lampshade", "a t.v remote", "chute", "roomfreshner", "beem", "vinegar", "plank", "helper", "fiber", "means", "fingernail", "pith", "photograph", "coarse", "buffer", "thick", "wastebasket", "showerhead", "spirit", "hairbrush", "nailcutte", "fungi", "person", "tequila", "cracker", "egg", "frame", "grape", "comb", "wet", "jig", "jelly", "naan", "woollen", "supper", "skillet", "femur", "cabe", "troll", "blowup", "salve", "tissue", "pushing", "vodacom", "vegetation", "plywood", "print", "unfolding stocking", "ship", "cleat", "citing", "swimming", "rail", "calculate", "toolbox", "camcorder", "coil", "sink", "flag", "pound", "cylinder", "crater", "gumball", "lotus", "wire", "kidney", "banister", "'sickle", "item", "shall", "crosswalk", "cuprisun", "healthdrink", "pony", "magnet", "dumbbell", "salt", "water", "boot", "pet", "melatonin", "sharpness", "fitting", "solid", "trunk", "speedometer", "kiss", "medicine", "hearing", "food", "ca", "a", "copybook", "elephant", "tulip", "something", "mobilephone", "skin", "stove", "juicy", "turkey", "torchlight", "rectangular", "adaptor", "log", "dough", "brave", "cardigan", "nugget", "closing", "background", "an i.d.", "bailed", "rob", "sprayer", "blister", "bilimbi", "equipment", "baby", "vehicle", "day", "pong", "cookie", "mood", "nova", "exact", "maracas", "nappy", "wick", "york", "tupperware", "garage", "am", "snack", "plot", "treadmill", "armature", "flashdisks", "lungi", "tip", "sugar", "straw", "gun", "elevator", "march", "baking", "pencil", "tomato", "light", "audio", "nightlight", "blood", "meet", "chappati", "vitamin", "currency", "lamtoro", "wear", "christmastime", "staircase", "dummies", "smartphones", "reader", "radish", "mahal", "biro", "assembly", "broomstick", "porcelain", "mora", "telecom", "cycling", "spectrum", "corainder", "bluetooth", "pistachio", "brooch", "pad", "source", "pain", "cocktail", "sliding", "cord", "figur", "nailfile", "ring", "dumdum", "document", "flow", "duck", "twig", "graveyard", "make", "t-shirts", "record", "circular", "journal", "sardine", "monopoly", "dalek", "sealed", "mail", "led", "jello", "conch", "top", "mortar", "middle", "booklet", "hotspot", "starfish", "suction", "fennel", "stamped", "mailbox", "lap", "credit", "waistcoat", "tamil", "jumpdrive", "jewelry", "soap", "2liter", "video", "bridge", "cot", "pour", "magazine", "steelbowl", "elf", "note", "rickshaw", "kukumber", "cue", "empty", "blender", "ladoo", "propane", "living", "bodylotion", "reindeer", "figure", "sleeper", "flyer", "dessert", "shirt", "diaperbag", "bicycle-bell", "suds", "airport", "squeeze", "awash", "mint", "funnel", "jewellery", "magnate", "chip", "pork", "pot", "beverage", "petrol", "mill", "mob", "binocular", "a trashcan", "strawberry", "carousel", "fishbowl", "felt", "waffle", "patron", "altimeter", "clutches", "flour", "harry", "feeding", "taskpane", "detail", "puppet", "petroleum", "presser", "pomegranate", "grid", "beam", "papaya", "saw", "dipper", "shaker", "closet", "ice", "mark", "lake", "chalkpieace", "mother", "building", "sandal", "sprite", "absorber", "thermostat", "stevens", "antiperspirant", "dime", "oi", "enamel", "craft", "one", "coathanger", "windowsill", "coca-cola", "template", "laminating", "a roll-on", "hel", "watercolour", "ransom", "gymnosperm", "silverware", "sim", "armadillo", "iron", "ac", "classroom", "clamp", "turnip", "scratch", "front", "a noodle", "tracker", "machine", "grease", "a safe", "refer", "soupe", "showered", "cut", "trolley", "toiletpaper", "snowing", "open", "compassion", "bow", "product", "soil", "fish", "ounce", "drumstick", "smartphone", "bedside", "bond", "coriander", "sweet", "cajuput", "fresher", "cranberry", "hedge", "fairy", "a needle", "stain", "abacus", "van", "soup", "plugged", "hex", "thermocol", "balance", "sons", "volume", "hate", "fairbanks", "alcohol", "leave", "loop", "cereal", "hair-oil", "canopener", "crocodile", "award", "rainbow", "bandana", "radio", "holder", "disney", "lunch", "hose", "pressure", "ribbon", "spigot", "gut", "cupholder", "skyscraper", "blackboard", "toilet", "buzz", "android", "violin", "beach", "decoder", "lemon", "cuttingplayer", "pail", "encyclopedia", "ingredient", "redchile", "gravy", "locate", "relish", "clothespin", "tigress", "sticker", "geometry", "binoculars", "equalizer", "kindle", "paperclip", "antacid", "dal", "second", "toiletry", "copier", "scotland", "nodule", "liquidate", "vodka", "aspiration", "lifeboat", "mason", "cabinet", "doll", "thumbnail", "reliever", "man", "nutcracker", "ceiling", "lipbalm", "charge", "crew", "ingredients", "banknote", "enclosure", "arrive", "poster", "garbage", "cigar", "gas", "cart", "curd", "driveway", "cuff", "graphic", "butter", "outer", "bulletin", "puller", "airconditioner", "zucchini", "coaster", "packaging", "tongs", "lunchbox", "slab", "place", "dropdown", "network", "inbuilt", "bed", "kibble", "writing", "tapeholder", "polymer", "press", "dawn", "a watercan", "hydrogen", "gloss", "cutlery", "espadrille", "either", "refresher", "massager", "tobacco", "sphere", "teabag", "hall", "jean", "sublight", "skittles", "bone", "date", "patty", "letter", "nipple", "plasticware", "wastebin", "blush", "point", "clarinet", "deod0rant", "balloon", "yoda", "pond", "raquel", "bracelet", "fluid", "evo", "wallclock", "packing", "dishwasher", "benz", "flashdrive", "typewriter", "playdough", "sensor", "rug", "3", "channel", "fortune", "mardi", "pack", "be", "larva", "storm", "magneto", "bamboo", "moving away", "violinist", "thrown", "popsicle", "brown", "module", "nutty", "dry", "ink", "perfume", "dairy", "close", "vest", "fog", "school", "sister", "war", "thing", "cajeput", "back", "tuner", "exterior", "rifle", "chapati", "truck", "grille", "debt", "pore", "nut", "bobby", "magnifier", "side", "medium", "purcell", "johnson", "seasoning", "park", "bird", "super", "clothclip", "joystick", "whiteboard", "exhaust", "nailcutter", "income", "marking", "game", "separate", "gulab", "swab", "len", "plant", "bikini", "slot", "chalkboard", "cashier", "cappuccino", "harelip", "sellotape", "mash", "grey", "schoolbag", "glycerin", "sachet", "health", "fixture", "sack", "showpiece", "television", "formation", "bleach", "liston", "brief", "notice", "3ds", "liner", "spider", "triangle", "shadow", "switchblade", "ziplock", "rabbit", "portion", "brits", "earrings", "agarbathy", "silk", "boxcutter", "shrub", "massage", "hub", "layer", "hairline", "input", "filing", "openner", "emblem", "gear", "internet", "fiona", "ladder", "casket", "avenue", "route", "matchbox", "train", "autoriksha", "raccoon", "con", "bin", "mug", "word", "picking", "listening", "pipeline", "ironborn", "putty", "ridge", "rode", "pilot", "transformer", "punch", "guinea", "raincoat", "cricket", "rubin", "speck", "mirror", "born", "peppershaker", "packet", "flap", "proposes", "sample", "transit", "dealer", "branch", "caesium", "slicer", "nest", "bittergaurd", "walking", "thumb", "showcase", "model", "handphone", "handful", "microwave", "snooze", "woodcutter", "projector", "harddisk", "kalu", "corn", "remove", "index", "hoop", "pocketknife", "posit", "filler", "couid", "disc", "pipe", "touched", "card", "coca", "salon", "peal", "arrow", "rose", "piano", "says", "candy", "guidebook", "music-player", "checkbook", "hamburger", "backwash", "tuna", "bitter", "pulley", "literate", "expanded", "dirty", "wind", "stationery", "teaspoon", "nourishment", "stickynote", "grip", "videogame", "others", "platter", "beard", "pair", "cutter", "heart", "earing", "yarn", "purifier", "chocolat", "burn", "bloc", "cable", "walnut", "nacho", "aspects", "die", "mellow", "carom", "tapir", "boy", "cocoa", "airscrew", "staple", "cherry", "condenser", "season", "ledge", "twine", "burger", "kimi", "weight", "shovel", "matching", "sanitizer", "fryer", "shop", "r", "logbook", "gangsing", "hulk", "kin", "alligator", "bathsoap", "muff", "hollow", "sweater", "snake", "graffiti", "glad", "shallow", "extreme", "domino", "door-bell", "holdall", "notebook", "candlewarmer", "sponge", "box", "mutton", "recycling", "koolaid", "mighty", "fang", "cellphone", "kitten", "earring", "dexter", "blurry", "varnish", "choker", "creamy", "headgear", "broom", "saree", "dip", "rasa", "mousse", "granola", "jagged", "dress", "lotion", "did", "eyeliner", "handler", "shoe", "crusher", "seltzer", "carrot", "winter", "colander", "rubies", "thimble", "injection", "ashtray", "stalker", "ambulance", "bourn", "wrap", "herb", "shuffle", "griddle", "payback", "headlight", "pinecone", "ot", "minion", "sockdrawer", "left", "insulation", "toothpick", "canvas", "nicholas", "thermosteel", "polishing", "plain", "pulse", "charger", "tearing leaves just a little", "thermos", "chestnut", "stained", "rop", "bill", "shit", "glove", "gaslight", "cardboard", "fairness", "square", "vas", "soccerball", "pepsodent", "datacard", "plat", "subscription", "root", "silencer", "tub", "softdrinks", "converter", "gin", "neck", "balsam", "euro", "nailclipper", "chapathi", "bike", "almond", "elmo", "extinguisher", "panty", "refined", "winnie", "weed", "pasta", "jute", "razor", "handwash", "airfreshner", "coffeemug", "cure", "traffic", "tin", "chilli", "michi", "chutney", "trimmer", "tara", "role", "take", "cloth", "jewel", "pajama", "drawer", "group", "short", "steamer", "flute", "patch", "vanity", "insulin", "orchid", "inbox", "sugarcane", "bathtub", "hydrant", "vent", "zelda", "antler", "melon", "concealer", "sleeve", "rate", "basket", "christmas", "prune", "grabber", "airpump", "duster", "hope", "gripped", "outside", "plettrum", "tire", "tender", "okra", "stainless", "station", "control", "ground", "trouser", "mine", "gras", "drained", "toy1", "sandstone", "underwire", "storage", "coloring", "keeper", "bandaid", "lime", "quarters", "clutch", "shower", "candles", "diva", "lumberjack", "bastille", "stalk", "cupcake", "corkscrew", "undershirt", "bonsai", "eggcup", "deposit", "freezer", "bouncy", "dragonfly", "knit", "asafoetida", "vegetables", "liqueur", "saucepan", "draw", "base", "fastener", "deodorizer", "discards", "creature", "rest", "dust", "en", "dragonfruits", "tropical", "remover", "flip", "come", "bark", "shark", "lint", "stuff", "turn", "mitts", "shear", "pairing", "scatchtape", "mitten", "cent", "wireplug", "parrot", "gasket", "watch", "tyre", "penguin", "tin-foil", "wax", "needle", "talkie", "cpu", "racket", "nightstand", "security", "bracket", "corrected", "droplet", "hemi", "clothclips", "lollypop", "accelerator", "stabilizer", "flipflop", "temple", "tablets", "aquaphor", "scissors", "suitcase", "lifter", "residing", "lottery", "mascara", "kaleidoscope", "prep", "groundnut", "flowerpot", "stair", "a v", "coke", "half", "snow", "luquidator", "butterknife", "agenda", "boil", "queen", "booking", "remedy", "crime", "cabbage", "cauliflower", "watering", "cucumber", "contact", "peanut", "skeleton", "watermelon", "laser", "coin", "diaper", "jug", "a t-shirt", "blackberry", "pawn", "blazer", "male", "handset", "keyring", "cam", "curling", "lodge", "multivitamin", "coffee", "tumbler", "keep", "laboratory", "m&m`s", "hindi", "crowd", "fridge", "headache", "puff-box", "nose", "invitation", "straighter", "key", "chapstick", "tape", "tennis", "pole", "clothesline", "coupon", "change", "hand", "flintstone", "hinge", "cow", "yam", "matter", "letterhead", "touch", "salsa", "ex", "surface", "outlet", "an olive", "tile", "calculator", "jacket", "perform", "pendant", "passion", "cork", "bendingpole", "littering", "wrist", "stick", "marcus", "washingmaschine", "pullover", "nail", "wristlet", "bouquet", "hangar", "rook", "an", "pledge", "jasmine", "bundle", "mix", "pin", "donald", "belt", "people", "cashew", "car", "lion", "cram", "action", "utility", "mitt", "calamari", "cement", "track", "tear", "player", "win", "viper", "dry chilly", "vanilla", "popcorn", "mango", "bomb", "compressor", "hay", "agarbatti", "guard", "cheaper", "bag", "sarong", "sling", "ricecooker", "baster", "metronome", "hook", "core", "spread", "clip", "hatchet", "regulate", "bookmaker", "snyder", "pubic", "neil polish", "fountain", "ups", "banner", "measuring", "shaver", "manual", "cotter", "cinnamon", "pampers", "shelf", "down", "lentils", "ruler", "bootie", "cellotape", "crash", "hacksaw", "stool", "edge", "clasp", "cardholder", "accessory", "tortoise", "silver", "polis", "bottlecap", "punching", "a flashdrive", "decoration", "madam", "barbell", "lot", "yellowbook", "gore", "flower", "samurai", "tie", "counter", "hairball", "miniature", "herald", "hob", "pillowcase", "steel", "walkie", "well", "shade", "crucifix", "loafer", "mini", "donkey", "eyeball", "puzzle", "rack", "hanger", "dye", "ware", "dishdrainer", "pant", "saddle", "mask", "acetaminophen", "insoles", "carrier", "agarpathi", "bindi", "cooler", "trigger", "ganapathi", "dishwashing", "incense", "hardbound", "tabletop", "debit", "toy", "wash", "soy", "pendulum", "showelgel", "basketball", "chin", "blouse", "angle", "saline", "flattop", "cube", "cone", "tweezers", "powder", "monument", "floss", "ventilator", "workshop", "games", "parcel", "beware", "steelbox", "tongue", "hotdog", "collate", "splitter", "lifebuoy", "crunchy", "parsley", "black-ink", "crepe", "hardest", "flex", "robot", "tablet", "noodle", "jenna", "line", "sunder", "fake", "dishcloth", "balloons", "strip", "piggyback", "expo", "pill", "drawing", "puma", "microphone", "collection", "sleeping", "bonbon", "joy", "cushion", "plushy", "beige", "mouth", "football", "photo", "shed", "cider", "muesli", "chain", "dashboard", "hanging", "calc", "dutch", "candlestick", "chapels", "dimmer", "term", "taperoll", "care", "paperweight", "organiser", "peg", "robin", "waist", "gamed", "film", "hardback", "peroxide", "idly", "spill", "neem", "reel", "potato", "hai", "pop", "multiple", "valid", "stereo", "one of many t-shirt", "indicator", "puck", "tote", "data", "rule", "bit", "toggle", "statue", "dirt", "velvet", "invoice", "shoot", "distribution", "lentil", "fuck", "stand", "carton", "ram", "lumber", "ethernet", "sweetmeat", "wish", "lay", "ration", "inhaler", "receiver", "powerbotton", "fluff", "stir", "recliner", "resin", "nailpolish", "factory", "spice", "makeup", "whitener", "milkmaid", "pate", "a dictionary", "power", "detector", "crust", "adapter", "shuttle", "latinum", "everyday", "greying", "fold", "phone", "sock", "butt", "thermo", "bobbin", "toaster", "stop", "a short", "connected", "spark", "calender", "or", "dosa", "symbol", "giv", "cheek", "dish", "auto", "elbow", "block", "chisel", "picked", "owen", "object", "walker", "cob", "tail", "morten", "heating", "wollen", "saucer", "sign", "phat", "whisk", "potty", "mayonnaise", "too", "pier", "tent", "dog", "potter", "tumble", "generator", "pug", "camphor", "wrapper", "vial", "\"h\"", "phenyl", "chappathi", "sprout", "mustache", "pane", "stroller", "starburst", "xerox", "paintbrush", "cofffe-jar", "witch", "tab", "bar", "crackpot", "wolf", "teddy", "grocery", "folder", "toe", "plunger", "glowsticks", "gallon", "marble", "earbuds", "atomizer", "biscuit", "'book", "ottoman", "honey", "casing", "sex", "wetware", "men", "datta", "hula", "foil", "palm", "staff", "anti", "topless", "flip-flop", "giftpack", "sportbottle", "armrest", "circle", "deodorants", "chap", "beet", "seatbelt", "earth", "dart", "icecream", "penstand", "chopstick", "watercolor", "direction", "compote", "fingerboard", "hello", "son", "inner", "vessel", "mud", "salad", "grinder", "bathroom", "figurine", "chest", "jump", "raises", "garden", "sectors", "squirt", "octopus", "corner", "nickel", "fist", "meal", "screwup", "maker", "unit", "jackfruit", "alkaline", "bunch", "tempeh", "bee", "dipstick", "cigarettes", "adhesive", "measure", "cupboard", "croissant", "rubber", "sunglass", "token", "wreath", "tablestopper", "dining", "flannel", "bible", "hunter", "palace", "aquarium", "curler", "oreo", "colour", "wound", "jaggery", "pickle", "pixie", "an aerial", "an m", "pita", "hershey", "mineral", "meand", "facebook", "potholes", "scream", "pig", "vape", "ceramic", "cayenne", "active", "fruit", "mixer-jar", "easter", "sunscreen", "yoghurt", "logo", "frock", "beater", "fabric", "envelope", "gate", "polenta", "textbook", "kerchief", "compass", "connection", "coat", "handtowel", "whirlpool", "driller", "sagebrush", "mover", "sport", "pencilcase", "plum", "bolt", "sandwich", "tray", "slide", "agarbathi", "velcro", "heat", "excel", "striker", "greenery", "pom", "mosque", "motorpump", "pool", "nub", "selector", "content", "birthday", "aftershave", "cub", "dims", "nib", "advertisement", "tiffin", "ballpoint", "powerplug", "cup", "burning", "tack", "vaporised", "fat", "lipstick", "stirring", "wineglass", "backpack", "enter", "brush", "surf", "drawstring", "leash", "router", "anklet", "build", "protein", "port", "burner", "piggy", "glow", "glucose", "airliner", "firebox", "capacitor", "seed", "valve", "glassball", "ladle", "headphones", "throwpillow", "brushed", "taj", "chapatti", "pretzel", "railing", "job", "lei", "mongoose", "gravel", "lame", "liars", "extend", "earmuffs", "wastebox", "paperback", "porter", "plate", "dot", "coffeemix", "zipper", "remote", "starch", "poking once so that it slightly moves", "biriyani", "strap", "bang", "pumping", "table", "bearing", "papertowel", "museum", "carry", "zoo", "culture", "acorn", "dinner", "lift", "sauce", "backyard", "leather-bag", "rattle", "refill", "gobbles", "toner", "swing", "leaftray", "panel", "embroidery", "fire", "bullet", "bumper", "bleacher", "news", "string", "ledger", "t-shirth", "electabuzz", "flight", "paste", "a comic", "rish", "cutting", "gorilla", "steelglass", "bronze", "clothes", "opener", "pudding", "dryer", "fishhook", "shallot", "cufflink", "style", "pen", "yoyo", "fluorescent", "heap", "one of many similar", "knot", "specimen", "dhoti", "burnt", "mope", "paper", "fiberglass", "chord", "spine", "beetroot", "processor", "dumpster", "seashell", "doraemon", "dustbin", "bacon", "eraser", "cookingpot", "container", "waterbottle2", "electronics", "moisturizer", "slippers", "odor", "flossed", "grime", "elastic", "frisbee", "kitchen", "scissor", "sand", "coversheet", "spectacle", "squirrel", "snip", "discard", "twin", "dresser", "drone", "carafe", "cool", "soft stuffed poodle", "bio", "wise", "plaster", "he", "lock", "pile", "pa", "tortilla", "hockey", "garlic", "liquid", "nesscaffe", "the can", "leg", "d.v.d", "kitty", "distributor", "aerosol", "aloe", "smoke", "catch", "kangaroo", "spade", "teams", "tipex-maus", "analogue", "chalk", "battleship", "dollar", "goofball", "margarine", "\"p\"", "videocamera", "twist", "outdoor", "\"o\"", "tapioca", "sol", "nesting", "garfield", "bookmark", "triple", "pistol", "pear", "vapor", "mouthwash", "cheekbone", "hyena", "glade", "shaving", "gulp", "keying", "stencil", "page", "crystal", "karate", "loco", "hole", "speaker", "tripod", "camera", "atta", "rajah", "webster", "textmarker", "makeupbrush", "metal", "brace", "papa", "soapcontainer", "tether", "cryo", "swan", "recipient", "cap", "blanket", "church", "sea", "vicks", "wooden", "skateboard", "knight", "scooter", "wristwatch", "truth", "vinyl", "lychee", "buff", "fireplace", "fox", "countertop", "fash", "wheat", "cassette", "shampoo", "lamp", "origami", "drink", "watt", "spate", "steak", "link", "headlamp", "rope", "zebra", "fall", "socket", "disk", "aircondition", "cannon", "flush", "cellophane", "bean", "bucket", "sunset", "chocolate", "k-cup", "ar", "plug", "litter", "batteries", "loader", "cleaning", "skirt", "compression", "town", "headphone", "lightbulb", "selfie", "eyewear", "placemat", "buckle", "gluestick", "candelabra", "textsurfer", "immersion", "tennisball", "shampoo-bottle", "manuel", "cello", "multi", "pigeons", "lawn", "pyramid", "plastic", "roller", "vaseline", "headset", "powered", "level", "recon", "doorstopper", "xmas", "a mobile", "rosary", "cash", "shutter", "trivet", "picker", "village", "washer", "sugarholder", "text", "lens", "bonnet", "pos-it", "broken", "boutonniere", "hairdryer", "vera", "clove", "rod", "grill", "series", "pie", "format", "sheer", "fuse", "marinas", "pringles", "axe", "maize", "mantis", "lacquer", "shitbox", "pan", "catalog", "puddy", "transparent", "cola", "dishpan", "ply", "lowercase", "someplace", "underwear", "scarf", "maple", "fresh", "spay", "latch", "pancake", "krishna", "sandpaper", "recap", "book/dvd case/booklet", "cheerio", "injector", "martini", "batterycell", "world", "fevicol", "smiley", "feather", "planner", "offset", "stolen", "glass", "movie", "rubbish", "from", "juicer", "swat", "washing", "beholder", "copper", "organizer", "master", "carmen", "pretend", "self", "cartoon", "remotecontroller", "lava", "lantern", "chuck", "air", "tics", "beaker", "ghee", "mushroom", "cream", "thea", "teflon", "thumbtack", "wad", "screen", "teatowel", "sackcloth", "'box", "kerosene", "chou", "mit", "nailpaint", "compartment", "utensils", "shal", "flamingo", "hippo", "memory", "cross", "gauze", "silicone", "paperboy", "id", "'torch", "panda", "asparagus", "study", "freeduino", "streetsign", "bottle", "juice", "dinosaur", "met", "gem", "rubberband", "beauty", "passport", "folk", "a rose", "soldier", "killer", "oscillograph", "household", "scotch", "spencer", "kamal", "lizard", "goals", "post-it", "delight", "phonebook", "badminton", "entrance", "bricheta", "forehead", "furniture", "mama", "eyebrow", "dedotarent", "absorbent", "inmost", "bud", "sill", "marla", "shashi", "ibex", "office", "donut", "way", "dia", "voucher", "tipp-ex", "raggedy", "book", "stress", "mate", "boardmarker", "fizz", "cream-box", "budweiser", "roast", "pincer", "land", "blue stuffed bear", "denim", "connector", "toy2", "vita", "porch", "so", "night", "nob", "break", "disinfectant", "dock", "signal", "sac", "matchboxes", "novel", "masking", "notepad", "supply", "mulch", "tower", "sweetener", "wine", "hansaplast", "spinning", "identity", "bungee", "roti", "nylon", "crutch", "yardstick", "earplugs", "floor", "bam", "ifl", "cottontail", "creme", "terminal", "prong", "banana", "end", "the pouch", "mural", "flier", "menthol", "wireless", "yogurt", "napkin", "shave", "dragon", "gatsby", "cough", "image", "stovetop", "jeep", "pasties", "ingot", "palette", "frying", "desk", "eyedropper", "electrician", "pensive", "flavoring 'royco'", "paper-clip", "sharpie", "kite", "tooth", "bottom", "bowl", "wallet", "stump", "user", "motor", "styrofoam", "creamer", "wool", "capsule", "love", "scalp", "woolen", "aluminium", "blushed", "blossom", "nailpolosh", "penny", "aeroplane", "confetti", "a vegetable", "mayo", "eyelash", "firecracker", "repeat", "horndog", "chem", "hotchpotch", "gourd", "thorn", "extension", "erase", "piece", "lavender", "ball", "holiday", "forefinger", "shoehorn", "damn", "poker", "laptop", "protector", "dispenser", "shoulder", "petal", "cage", "turmeric", "slider", "browser", "tester", "serum", "glitter", "santa", "director", "grass", "stake", "oil", "stone", "rain", "pallet", "cooker", "cat", "polish", "extractor", "switch", "puffed", "hygrometer", "hotel", "can", "angels", "flyswatter", "coffe", "visors", "usb-stick", "painting", "crane", "marshmallow", "bath", "butterfly", "library", "dandelion", "can't", "doctor", "nano", "backing", "utensil", "map", "bodywash", "construction", "dill", "ab", "nice", "crippledsign", "peel", "buddha", "bastard", "board", "stumped", "pamphlet", "mallet", "sheep", "stuffed", "jack", "prenjak", "slip", "spindle", "dagger", "column", "capo", "manga", "flop", "collector", "crapola", "attachment", "teagarden", "theater", "onion", "rice", "ebb", "bowtie", "juggling", "rock", "slime", "gatorade", "doormat", "a remote", "usb", "pepper", "apple", "sharpener", "drill", "bedroom", "swatter", "underline", "safe", "scent", "knacksac", "veg", "candle", "octagon", "crown", "pillow", "mustard", "pele", "casserole", "wall", "electricbox", "plasticbag", "eatable", "pestle", "guide", "husk", "monitor", "stein", "pepsi", "mechanism", "brick", "notizheft", "mandarin", "bending", "goat", "shot", "tread", "guess", "cycle", "parapet", "bear", "i", "rein", "eclair", "magic", "lighter", "newsstand", "camel", "shawl", "highlighter", "advertising", "interior", "story", "rag", "section", "coup", "deodorant", "chew", "bat", "sake", "silica", "spreader", "filter", "snowglobe", "talcum", "chewing", "island", "shifu", "raisin", "serving", "jupiter", "stamp", "bingbang", "recorder", "prism", "cops", "pamper", "stem", "company", "hanky", "deal", "energy", "headstone", "stucco", "based", "washbasin", "fry", "flake", "a flip-flop", "divider", "tailor", "energon", "gaming", "rust", "reading", "burlap", "coffeepot", "snail", "mac", "stud", "sari", "paddle", "0,10\u20ac", "maroon", "statuette", "opine", "spot", "seiya", "jar", "jawbone", "view", "playingcard", "mellows", "antenna", "newsprint", "chair", "bookshelf", "pattern", "sausage", "clothe", "checker", "thimblethimble", "choco", "multivatimins", "receipt", "steam", "umbrella", "champagne", "comp", "oat", "teeshirt", "signboard", "heel", "sitch", "ticket", "giraffe", "holster", "loofah", "lanyard", "loaf", "sportshoe", "hotbox", "bun", "put", "name", "headboard", "hoodie", "pocket", "lincoln", "bearer", "hedgehog", "owner", "fei", "motorcycle", "match", "envelop", "peace", "tank", "lactose", "tiger", "spinner", "scanner", "keywords", "whistle", "ornament", "crochet", "driver", "gotta", "set", "home", "twelve", "shuttlecock", "pearl", "gal", "briefcase", "tamarind", "votive", "define", "winner", "antennas", "net", "web", "rub", "roofer", "couch", "sieve", "squeezer", "cooped", "sprinkler", "suki", "condom", "soybean", "bowler", "modem", "nasal", "jersey", "knife", "pink", "scatter", "thermometer", "bus", "inboard", "admiral", "stopper", "10\u20ac", "skate", "alpenliebe", "relief", "album", "kota", "goodnight", "wing", "clipper", "dummy", "cigarette", "pic", "tong", "sweeper", "wheeler", "handout", "instrument", "small", "market", "bunny", "eco", "solder", "glycerine", "wafer", "ache", "staples", "liquor", "slinky", "cumin", "optic", "shrek", "feeder", "meter", "playstation", "furball", "doily", "tetrapack", "divan", "emoji", "prescription", "re", "lord", "cock", "olive", "cover", "claro", "spoil", "masala", "millimeter", "mop", "pineapple", "pizza", "wipe", "scenary", "haircomb", "woman", "cleaner", "childrens", "chicken", "gummy", "presume", "curtain", "calendar", "penlight", "cell", "six", "pinwheel", "wedge", "couple", "hairpin", "carving", "muscle", "amplifier", "ten", "surge", "show", "silver top", "muffin", "photo-frame", "unfolding", "sewing", "ranch", "soccer", "ping", "wicker", "taschent\u00fccher", "price", "malaysia", "cake", "a post-it", "fragrance", "waterboard", "body", "component", "split", "forget", "girl", "powerball", "collar", "swicthbox", "mainswitch", "sharper", "facemassager", "toffee", "coffeecup", "move", "shape", "menu", "foam", "doorknob", "room", "dice", "copy", "vacuum", "virgin", "boll", "ash", "smurf", "screw", "perforated", "pantyliners", "softener", "dustpan", "engine", "matrioska", "banjo", "pomade", "privy", "slant", "argue", "horlicks", "human", "dew", "sniffer", "keyboard", "birdcage", "doh", "detergent", "color", "play", "particle", "diary", "jetpack", "drive", "popper", "slice", "roundabout", "snacks-box", "survey", "material", "laundry", "tractor", "travel", "recipe", "odd", "'packet", "handbag", "knob", "bread", "scooper", "pocahontas", "triangular", "chilly", "round", "fence", "doth", "portrait", "hammer", "induction", "refrigerator", "circuit", "scale", "mp3 casing", "a mp3", "manila", "bangle", "play-do", "helmet", "insert", "golf", "bod", "badass", "mic", "nozzle", "controller", "sickle", "sterilize", "cringe", "clothing", "squash", "starters", "to", "plane", "frog", "horn", "recant", "click", "brandy", "fan", "binder", "multitool", "teacup", "mat", "buddy", "umperla", "keyhole", "batch", "walkman", "sim-card", "kit", "newspaper", "mouse", "gangsta", "uniform", "trip", "money", "booth", "brass", "pacifier", "roll", "yellow", "nonstick", "setsquare", "petridish", "pulp", "chime", "mixed", "violet", "deck", "flowerwise", "teddybear", "purse", "flosspik", "videotape", "wifi", "song", "fluffy", "amp", "motorbike", "smarties", "hair", "concrete", "bouncing", "yoga"], "list_classes_test_verb": ["throw", "stops", "tilting", "stacking", "deflected", "burying", "pushing", "fall", "does", "approaching", "poke", "spilling", "come", "stuffing", "glide", "failing", "turn", "tearing", "be", "touching", "slides", "wipe", "spinning", "wiping", "bending", "drop", "close", "squeezing", "is", "removing", "bend", "sprinkle", "something", "starts", "unfolding", "stretched", "throwing", "piling", "closing", "wringing", "covering", "fit", "open", "move", "rolling", "moves", "stays", "left", "overflows", "folding", "gets", "digging", "dropping", "attach", "collide", "scoop", "collapsing", "support", "pretending", "missing", "lifting", "spins", "plugging", "trying", "deforms", "comes", "put", "colliding", "holding", "laying", "filming", "catching", "putting", "picking", "moving", "pass", "falling", "scooping", "sliding", "twisting", "stick", "pouring", "showing", "separates", "pick", "take", "revealing", "twist", "uncovering", "hitting", "rolls", "tipping", "poking", "slide", "stand", "are", "being", "spills", "remove", "right", "continues", "pour", "roll", "supported", "spread", "turning", "breaks", "attaching", "sprinkling", "squeeze", "pulling", "falls", "letting", "taking", "spreading", "opening"]}